LICENSE
README.md
setup.py
automacao_blaze_cassino/__init__.py
automacao_blaze_cassino/chrome.py
automacao_blaze_cassino.egg-info/PKG-INFO
automacao_blaze_cassino.egg-info/SOURCES.txt
automacao_blaze_cassino.egg-info/dependency_links.txt
automacao_blaze_cassino.egg-info/requires.txt
automacao_blaze_cassino.egg-info/top_level.txt