Metadata-Version: 2.4
Name: automacao-blaze-cassino
Version: 0.1.0
Summary: Automatização do site Blaze usando Selenium
Home-page: https://github.com/autodev/automacao-blaze
Author: Auto Dev
Author-email: autodev331@gmail.com
Classifier: Programming Language :: Python :: 3
Classifier: License :: OSI Approved :: MIT License
Requires-Python: >=3.7
License-File: LICENSE
Requires-Dist: selenium>=4.0.0
Requires-Dist: webdriver-manager>=3.8.0
Dynamic: author
Dynamic: author-email
Dynamic: classifier
Dynamic: description
Dynamic: description-content-type
Dynamic: home-page
Dynamic: license-file
Dynamic: requires-dist
Dynamic: requires-python
Dynamic: summary
